[
  {
    "text": "Here's a fun little exploration I finally got to turn into something real. (I was thinking about this back in 2020 and got derailed).\n\nWhat if we could make visualizations for the running state of our programs not by augmenting them inline with traces and prints, nor creating a vm in our language to high-jack the execution and record what we want, but instead our language itself could talk about its own execution?\n\nI put together a little proof of concept of such a language. It is just a little term rewriting language, but in it you have meta rules that will match on the execution of the programming itself (I do not yet have meta meta rules (ad infinitum), but there is nothing at all that would stop you from doing this and if I made this real I'd definitely do it).\n\n<https://jimmyhmiller.com/term-rewriting-experiment-one>",
    "files": [
      {
        "id": "F0AHA82AJ0Y",
        "created": 1771806558,
        "timestamp": 1771806558,
        "mimetype": "image/png",
        "filetype": "png",
        "pretty_type": "PNG",
        "user": "UK3LH8CF5",
        "user_team": "T5TCAFTA9",
        "editable": false,
        "size": 659070,
        "mode": "hosted",
        "is_external": false,
        "external_type": "",
        "is_public": true,
        "public_url_shared": false,
        "display_as_bot": false,
        "username": "",
        "name": "Screenshot 2026-02-22 at 7.28.19 PM.png",
        "title": "Screenshot 2026-02-22 at 7.28.19 PM.png",
        "url_private": "https://files.slack.com/files-pri/T5TCAFTA9-F0AHA82AJ0Y/screenshot_2026-02-22_at_7.28.19___pm.png",
        "url_private_download": "https://files.slack.com/files-pri/T5TCAFTA9-F0AHA82AJ0Y/download/screenshot_2026-02-22_at_7.28.19___pm.png",
        "media_display_type": "unknown",
        "thumb_64": "https://files.slack.com/files-tmb/T5TCAFTA9-F0AHA82AJ0Y-9aa6c1244a/screenshot_2026-02-22_at_7.28.19___pm_64.png",
        "thumb_80": "https://files.slack.com/files-tmb/T5TCAFTA9-F0AHA82AJ0Y-9aa6c1244a/screenshot_2026-02-22_at_7.28.19___pm_80.png",
        "thumb_360": "https://files.slack.com/files-tmb/T5TCAFTA9-F0AHA82AJ0Y-9aa6c1244a/screenshot_2026-02-22_at_7.28.19___pm_360.png",
        "thumb_360_w": 360,
        "thumb_360_h": 275,
        "thumb_480": "https://files.slack.com/files-tmb/T5TCAFTA9-F0AHA82AJ0Y-9aa6c1244a/screenshot_2026-02-22_at_7.28.19___pm_480.png",
        "thumb_480_w": 480,
        "thumb_480_h": 366,
        "thumb_160": "https://files.slack.com/files-tmb/T5TCAFTA9-F0AHA82AJ0Y-9aa6c1244a/screenshot_2026-02-22_at_7.28.19___pm_160.png",
        "thumb_720": "https://files.slack.com/files-tmb/T5TCAFTA9-F0AHA82AJ0Y-9aa6c1244a/screenshot_2026-02-22_at_7.28.19___pm_720.png",
        "thumb_720_w": 720,
        "thumb_720_h": 550,
        "thumb_800": "https://files.slack.com/files-tmb/T5TCAFTA9-F0AHA82AJ0Y-9aa6c1244a/screenshot_2026-02-22_at_7.28.19___pm_800.png",
        "thumb_800_w": 800,
        "thumb_800_h": 611,
        "thumb_960": "https://files.slack.com/files-tmb/T5TCAFTA9-F0AHA82AJ0Y-9aa6c1244a/screenshot_2026-02-22_at_7.28.19___pm_960.png",
        "thumb_960_w": 960,
        "thumb_960_h": 733,
        "thumb_1024": "https://files.slack.com/files-tmb/T5TCAFTA9-F0AHA82AJ0Y-9aa6c1244a/screenshot_2026-02-22_at_7.28.19___pm_1024.png",
        "thumb_1024_w": 1024,
        "thumb_1024_h": 782,
        "original_w": 2484,
        "original_h": 1896,
        "thumb_tiny": "AwAlADDQx0pdopFPOM9ulOGPWgBNo9KNqntS0DpxQAmxfSkZFCk4p2DQ33T9KAEWkVWAGWBI479Pz/WjGVxngilw24ksMdgB/P8AyKAHUg6UtIOlAC0jfdP0paRvun6UAC/dH0paRfuj6UtABRRRQAUjfdP0paRvun6UAf/Z",
        "permalink": "https://feelingofcomputing.slack.com/files/UBN9AFS0N/F0AHA82AJ0Y/screenshot_2026-02-22_at_7.28.19___pm.png",
        "permalink_public": "https://slack-files.com/T5TCAFTA9-F0AHA82AJ0Y-0847be1de3",
        "is_starred": false,
        "skipped_shares": true,
        "has_rich_preview": false,
        "file_access": "visible"
      }
    ],
    "upload": false,
    "user": "UK3LH8CF5",
    "display_as_bot": false,
    "blocks": [
      {
        "type": "rich_text",
        "block_id": "JWiPU",
        "elements": [
          {
            "type": "rich_text_section",
            "elements": [
              {
                "type": "text",
                "text": "Here's a fun little exploration I finally got to turn into something real. (I was thinking about this back in 2020 and got derailed).\n\nWhat if we could make visualizations for the running state of our programs not by augmenting them inline with traces and prints, nor creating a vm in our language to high-jack the execution and record what we want, but instead our language itself could talk about its own execution?\n\nI put together a little proof of concept of such a language. It is just a little term rewriting language, but in it you have meta rules that will match on the execution of the programming itself (I do not yet have meta meta rules (ad infinitum), but there is nothing at all that would stop you from doing this and if I made this real I'd definitely do it).\n\n"
              },
              {
                "type": "link",
                "url": "https://jimmyhmiller.com/term-rewriting-experiment-one"
              }
            ]
          }
        ]
      }
    ],
    "type": "message",
    "ts": "1771807273.217019",
    "client_msg_id": "c9fc4104-8688-4dc2-9177-d6f5619a09b9",
    "thread_ts": "1771807273.217019",
    "reply_count": 10,
    "reply_users_count": 5,
    "latest_reply": "1773848561.521409",
    "reply_users": [
      "UC2A2ARPT",
      "UK3LH8CF5",
      "UA14TGLTC",
      "U02U0AS3J49",
      "U0887QU9G2V"
    ],
    "is_locked": false,
    "subscribed": false,
    "reactions": [
      {
        "name": "star-struck",
        "users": [
          "U0AG84TGM3L",
          "UMQ6LR9NZ",
          "UA14TGLTC",
          "U0AGU6Q85KK",
          "UJBAJNFLK",
          "UMHG81CBH",
          "U02E4DAQGSZ",
          "UMV4B97GT",
          "U02U0AS3J49",
          "UML4ZEKDK"
        ],
        "count": 10
      },
      {
        "name": "raised_hands",
        "users": [
          "U09LA28NZFT",
          "U02E4DAQGSZ"
        ],
        "count": 2
      }
    ],
    "channel_name": "share-your-work",
    "channel_id": "CCL5VVBAN"
  },
  {
    "user": "UC2A2ARPT",
    "type": "message",
    "ts": "1771809481.595419",
    "edited": {
      "user": "UC2A2ARPT",
      "ts": "1771809492.000000"
    },
    "client_msg_id": "7dd4d970-dec8-4126-bf43-86f216b88330",
    "text": "ah that's a fun idea. i've passed this along to june (who made <http://nova-lang.net|nova>) since it seems like the sort of thing that'd be super easy to do in that language. will let you know if hijinks ensues.",
    "team": "T5TCAFTA9",
    "thread_ts": "1771807273.217019",
    "parent_user_id": "UK3LH8CF5",
    "blocks": [
      {
        "type": "rich_text",
        "block_id": "bGx5c",
        "elements": [
          {
            "type": "rich_text_section",
            "elements": [
              {
                "type": "text",
                "text": "ah that's a fun idea. i've passed this along to june (who made "
              },
              {
                "type": "link",
                "url": "http://nova-lang.net",
                "text": "nova"
              },
              {
                "type": "text",
                "text": ") since it seems like the sort of thing that'd be super easy to do in that language. will let you know if hijinks ensues."
              }
            ]
          }
        ]
      }
    ],
    "channel_name": "share-your-work",
    "channel_id": "CCL5VVBAN"
  },
  {
    "user": "UK3LH8CF5",
    "type": "message",
    "ts": "1771809972.156359",
    "client_msg_id": "9539204e-de95-4e58-818f-210561a7870d",
    "text": "Yeah, I just discovered nova. Looks really nice. Great to see more term rewriting based things. Definitely an under explored paradigm",
    "team": "T5TCAFTA9",
    "thread_ts": "1771807273.217019",
    "parent_user_id": "UK3LH8CF5",
    "blocks": [
      {
        "type": "rich_text",
        "block_id": "luGm6",
        "elements": [
          {
            "type": "rich_text_section",
            "elements": [
              {
                "type": "text",
                "text": "Yeah, I just discovered nova. Looks really nice. Great to see more term rewriting based things. Definitely an under explored paradigm"
              }
            ]
          }
        ]
      }
    ],
    "reactions": [
      {
        "name": "heavy_plus_sign",
        "users": [
          "UJBAJNFLK"
        ],
        "count": 1
      }
    ],
    "channel_name": "share-your-work",
    "channel_id": "CCL5VVBAN"
  },
  {
    "user": "UA14TGLTC",
    "type": "message",
    "ts": "1771821802.274099",
    "client_msg_id": "936a832a-a19b-4d72-9d50-69369dc07511",
    "text": "\"but instead our language itself could talk about its own execution\" <@UK3LH8CF5> you are trolling me.  Look up Aspect Oriented Programming.  You're welcome.  :nerd_face:",
    "team": "T5TCAFTA9",
    "thread_ts": "1771807273.217019",
    "parent_user_id": "UK3LH8CF5",
    "blocks": [
      {
        "type": "rich_text",
        "block_id": "LSyZa",
        "elements": [
          {
            "type": "rich_text_section",
            "elements": [
              {
                "type": "text",
                "text": "\"but instead our language itself could talk about its own execution\" "
              },
              {
                "type": "user",
                "user_id": "UK3LH8CF5"
              },
              {
                "type": "text",
                "text": " you are trolling me.  Look up Aspect Oriented Programming.  You're welcome.  "
              },
              {
                "type": "emoji",
                "name": "nerd_face",
                "unicode": "1f913"
              }
            ]
          }
        ]
      }
    ],
    "channel_name": "share-your-work",
    "channel_id": "CCL5VVBAN"
  },
  {
    "user": "UJBAJNFLK",
    "type": "message",
    "ts": "1771836000.920559",
    "client_msg_id": "5fef08c3-3372-4e1c-9d77-01640d7662e3",
    "text": "The difference between math and a visualization created by simulation is similar to the difference between a datasheet for a product and a video clip advertising the same product. The former encourages critical engagement, the latter encourages quick emotional judgment. An in-depth appreciation requires both.\n\nGeocentrism vs. heliocentrism is perhaps the most misunderstood story in the history of science. Neither one is right, nor wrong. You can freely pick any point in the universe as the reference from which to measure everything. Your left eye is just as \"right\" a choice as the center of whatever celestial body. The difference is in the convenience for doing the subsequent math. Yes, that difference can be enormously important. Which is why the shift from geocentrism to heliocentrism was such a major event: it opened the way to much more powerful models of the solar system, by greatly simplifying the mathematical descriptions. But if you consider the state of knowledge e.g. in the middle ages, there was no reason to even consider anything else than geocentrism. Geometry wasn't sufficiently advanced yet to make heliocentrism useful, algebra was hardly known in most parts of the world. and the very idea of calculus with its infinities would have seemed crazy to any scholar of the time.\n\nInterestingly, modern math notation and the transition to heliocentrism happened at roughly the same time.",
    "team": "T5TCAFTA9",
    "thread_ts": "1771729443.525989",
    "parent_user_id": "UGWUJUZHT",
    "blocks": [
      {
        "type": "rich_text",
        "block_id": "IP7Dg",
        "elements": [
          {
            "type": "rich_text_section",
            "elements": [
              {
                "type": "text",
                "text": "The difference between math and a visualization created by simulation is similar to the difference between a datasheet for a product and a video clip advertising the same product. The former encourages critical engagement, the latter encourages quick emotional judgment. An in-depth appreciation requires both.\n\nGeocentrism vs. heliocentrism is perhaps the most misunderstood story in the history of science. Neither one is right, nor wrong. You can freely pick any point in the universe as the reference from which to measure everything. Your left eye is just as \"right\" a choice as the center of whatever celestial body. The difference is in the convenience for doing the subsequent math. Yes, that difference can be enormously important. Which is why the shift from geocentrism to heliocentrism was such a major event: it opened the way to much more powerful models of the solar system, by greatly simplifying the mathematical descriptions. But if you consider the state of knowledge e.g. in the middle ages, there was no reason to even consider anything else than geocentrism. Geometry wasn't sufficiently advanced yet to make heliocentrism useful, algebra was hardly known in most parts of the world. and the very idea of calculus with its infinities would have seemed crazy to any scholar of the time.\n\nInterestingly, modern math notation and the transition to heliocentrism happened at roughly the same time."
              }
            ]
          }
        ]
      }
    ],
    "channel_name": "linking-together",
    "channel_id": "C5U3SEW6A"
  },
  {
    "user": "UK3LH8CF5",
    "type": "message",
    "ts": "1771846869.122969",
    "client_msg_id": "EDAFE5E1-C462-45E2-B308-E70E8B4FE4D7",
    "text": "Yeah I'm familiar. I've even read Warren Teitelman’s thesis where advice comes from. But I think at least in the implementation what I have is a bit different.\n\n\n`fib(5)`*→ `add(fib(sub(5, 1)), fib(sub(5, 2)))`*\n\n \nI don't know any aspect that lets you get things like this. They instead are about function boundaries. (Pardon the bad formatting, on mobile)",
    "team": "T5TCAFTA9",
    "thread_ts": "1771807273.217019",
    "parent_user_id": "UK3LH8CF5",
    "blocks": [
      {
        "type": "rich_text",
        "block_id": "IQy6j",
        "elements": [
          {
            "type": "rich_text_section",
            "elements": [
              {
                "type": "text",
                "text": "Yeah I'm familiar. I've even read Warren Teitelman’s thesis where advice comes from. But I think at least in the implementation what I have is a bit different."
              },
              {
                "type": "text",
                "text": "\n\n"
              },
              {
                "type": "text",
                "text": "\n"
              },
              {
                "type": "text",
                "text": "fib(5)",
                "style": {
                  "code": true
                }
              },
              {
                "type": "text",
                "text": "→ ",
                "style": {
                  "bold": true,
                  "italic": false
                }
              },
              {
                "type": "text",
                "text": "add(fib(sub(5, 1)), fib(sub(5, 2)))",
                "style": {
                  "bold": true,
                  "italic": false,
                  "code": true
                }
              },
              {
                "type": "text",
                "text": "\n",
                "style": {
                  "bold": true,
                  "italic": false,
                  "code": true
                }
              },
              {
                "type": "text",
                "text": "\n",
                "style": {
                  "code": true
                }
              },
              {
                "type": "text",
                "text": " \nI don't know any aspect that lets you get things like this"
              },
              {
                "type": "text",
                "text": "."
              },
              {
                "type": "text",
                "text": " They instead are about function boundaries"
              },
              {
                "type": "text",
                "text": "."
              },
              {
                "type": "text",
                "text": " (Pardon the bad formatting, on mobile)"
              }
            ]
          }
        ]
      }
    ],
    "channel_name": "share-your-work",
    "channel_id": "CCL5VVBAN"
  },
  {
    "user": "UA14TGLTC",
    "type": "message",
    "ts": "1771876120.152529",
    "client_msg_id": "d46cd9b2-62fe-41ff-9ac1-20eb5193ff04",
    "text": "Probably a little different.  What's the \"this\" you have exactly in mind?  Being able advise evaluation in the way your meta rules do?  I think this demo super neat and would love to understand better.",
    "team": "T5TCAFTA9",
    "thread_ts": "1771807273.217019",
    "parent_user_id": "UK3LH8CF5",
    "blocks": [
      {
        "type": "rich_text",
        "block_id": "eA12J",
        "elements": [
          {
            "type": "rich_text_section",
            "elements": [
              {
                "type": "text",
                "text": "Probably a little different.  What's the \"this\" you have exactly in mind?  Being able advise evaluation in the way your meta rules do?  I think this demo super neat and would love to understand better."
              }
            ]
          }
        ]
      }
    ],
    "channel_name": "share-your-work",
    "channel_id": "CCL5VVBAN"
  },
  {
    "user": "U09LA28NZFT",
    "type": "message",
    "ts": "1771876344.652199",
    "client_msg_id": "de6b10ef-dfef-47b9-9d11-8a451e6cf208",
    "text": "<@UGWUJUZHT> For you is “writing code that writes code” an attitude that supports “designing the design” or is it more related to “buffing”?",
    "team": "T5TCAFTA9",
    "thread_ts": "1771596314.639699",
    "parent_user_id": "UGWUJUZHT",
    "blocks": [
      {
        "type": "rich_text",
        "block_id": "h1Cgu",
        "elements": [
          {
            "type": "rich_text_section",
            "elements": [
              {
                "type": "user",
                "user_id": "UGWUJUZHT"
              },
              {
                "type": "text",
                "text": " For you is “writing code that writes code” an attitude that supports “designing the design” or is it more related to “buffing”?"
              }
            ]
          }
        ]
      }
    ],
    "channel_name": "thinking-together",
    "channel_id": "C5T9GPWFL"
  },
  {
    "user": "UA14TGLTC",
    "type": "message",
    "ts": "1771876364.398549",
    "client_msg_id": "bc54b07c-4bfe-4c17-843b-dc19a7940e46",
    "text": "Do you think <@UJBAJNFLK> it might be that engaging with the math notation causes an implicit check on your understanding?  Like if you don't seriously understand a visualization you can go off vibes, but when you miss something about notated math you'll know you're lost?",
    "team": "T5TCAFTA9",
    "thread_ts": "1771729443.525989",
    "parent_user_id": "UGWUJUZHT",
    "blocks": [
      {
        "type": "rich_text",
        "block_id": "ev/Em",
        "elements": [
          {
            "type": "rich_text_section",
            "elements": [
              {
                "type": "text",
                "text": "Do you think "
              },
              {
                "type": "user",
                "user_id": "UJBAJNFLK"
              },
              {
                "type": "text",
                "text": " it might be that engaging with the math notation causes an implicit check on your understanding?  Like if you don't seriously understand a visualization you can go off vibes, but when you miss something about notated math you'll know you're lost?"
              }
            ]
          }
        ]
      }
    ],
    "channel_name": "linking-together",
    "channel_id": "C5U3SEW6A"
  },
  {
    "user": "UK3LH8CF5",
    "type": "message",
    "ts": "1771878004.584279",
    "client_msg_id": "4d2cc9fa-64a6-4e79-869f-9b491a064d3d",
    "text": "So at the limit, the whole entire language is just meta rules. Or a tower of meta rules. Meta rules not only see the computation, they can decide to change it. We can change our evaluation order from strict to lazy for example.\n\nMeta rules also can play the rules of macros but at a global level. They are a metaprogram that is given not only the static definition of the code, but all the code at every step in the execution.",
    "team": "T5TCAFTA9",
    "thread_ts": "1771807273.217019",
    "parent_user_id": "UK3LH8CF5",
    "blocks": [
      {
        "type": "rich_text",
        "block_id": "TyDCg",
        "elements": [
          {
            "type": "rich_text_section",
            "elements": [
              {
                "type": "text",
                "text": "So at the limit, the whole entire language is just meta rules. Or a tower of meta rules. Meta rules not only see the computation, they can decide to change it. We can change our evaluation order from strict to lazy for example.\n\nMeta rules also can play the rules of macros but at a global level. They are a metaprogram that is given not only the static definition of the code, but all the code at every step in the execution."
              }
            ]
          }
        ]
      }
    ],
    "reactions": [
      {
        "name": "+1",
        "users": [
          "UJBAJNFLK"
        ],
        "count": 1
      }
    ],
    "channel_name": "share-your-work",
    "channel_id": "CCL5VVBAN"
  },
  {
    "user": "UGWUJUZHT",
    "type": "message",
    "ts": "1771878699.540779",
    "edited": {
      "user": "UGWUJUZHT",
      "ts": "1771880503.000000"
    },
    "client_msg_id": "8423ee95-7a5b-4951-aab5-53b1e954029a",
    "text": "<@U09LA28NZFT> It can be used for both. I tend to (over?) favour the weakest link, so right now, I think in terms of just designing the design and making it possible to backtrack, erase what I’ve done and start over again without feeling a lot of friction. I used to use Lisp for such friction-less retreading, but t2t makes it even easier in my mind. I approach it with a ‘sed’ or `.replace(…)` attitude and I use multiple stages, so that I can focus on doing only one thing at a time. I once converted a big Pascal program to K&R C using VI and regex replacements only. I just kept nipping away at the file - eyeballing the partially transmogrified code and getting inspiration on what to replace next. I think of OhmJS as a super-regex (I mean to say ‘t2t’, which is OhmJS plus a tiny rewriter DSL that bolts onto OhmJS). As I see it, buffing code is already (overly?) well handled, so all I need to do is convert what I want to say into some already-existing language, then let it do all of the buffing and optimization. My recent foray into the guts of Forth Haiku shows that it does both - it produces mediocre code very, very easily, then rewrites it with an optimizer - it was all done in Javascript, so it can’t be all that hard :slightly_smiling_face:. 2 lines of forth-like code produces 400 lines (iirc) of Javascript which then gets rewritten as GLSL and produces pretty pictures on my monitor. (I can point to my YouTubes that attempt to explain the first part (thus far)).\n_aside: literally at this moment, I’m looking at a pipeline (10 ultra simple passes) that converts a really, really ugly lump of XML into 13 lines of less-ugly code. (The XML is a drawing saved out as graphML, the 13 lines is an intermediate form which I intend to convert to JSON and interpret/compile into running code)._",
    "team": "T5TCAFTA9",
    "thread_ts": "1771596314.639699",
    "parent_user_id": "UGWUJUZHT",
    "blocks": [
      {
        "type": "rich_text",
        "block_id": "j6dlx",
        "elements": [
          {
            "type": "rich_text_section",
            "elements": [
              {
                "type": "user",
                "user_id": "U09LA28NZFT"
              },
              {
                "type": "text",
                "text": " It can be used for both. I tend to (over?) favour the weakest link, so right now, I think in terms of just designing the design and making it possible to backtrack, erase what I’ve done and start over again without feeling a lot of friction. I used to use Lisp for such friction-less retreading, but t2t makes it even easier in my mind. I approach it with a ‘sed’ or "
              },
              {
                "type": "text",
                "text": ".replace(…)",
                "style": {
                  "code": true
                }
              },
              {
                "type": "text",
                "text": " attitude and I use multiple stages, so that I can focus on doing only one thing at a time. I once converted a big Pascal program to K&R C using VI and regex replacements only. I just kept nipping away at the file - eyeballing the partially transmogrified code and getting inspiration on what to replace next. I think of OhmJS as a super-regex (I mean to say ‘t2t’, which is OhmJS plus a tiny rewriter DSL that bolts onto OhmJS). As I see it, buffing code is already (overly?) well handled, so all I need to do is convert what I want to say into some already-existing language, then let it do all of the buffing and optimization. My recent foray into the guts of Forth Haiku shows that it does both - it produces mediocre code very, very easily, then rewrites it with an optimizer - it was all done in Javascript, so it can’t be all that hard "
              },
              {
                "type": "emoji",
                "name": "slightly_smiling_face",
                "unicode": "1f642"
              },
              {
                "type": "text",
                "text": ". 2 lines of forth-like code produces 400 lines (iirc) of Javascript which then gets rewritten as GLSL and produces pretty pictures on my monitor. (I can point to my YouTubes that attempt to explain the first part (thus far)).\n"
              },
              {
                "type": "text",
                "text": "aside: literally at this moment, I’m looking at a pipeline (10 ultra simple passes) that converts a really, really ugly lump of XML into 13 lines of less-ugly code. (The XML is a drawing saved out as graphML, the 13 lines is an intermediate form which I intend to convert to JSON and interpret/compile into running code).",
                "style": {
                  "italic": true
                }
              }
            ]
          }
        ]
      }
    ],
    "channel_name": "thinking-together",
    "channel_id": "C5T9GPWFL"
  },
  {
    "user": "U09LA28NZFT",
    "type": "message",
    "ts": "1771887973.425209",
    "client_msg_id": "c1970bfb-6a35-436f-a6cf-637e3dd5e234",
    "text": "<@UGWUJUZHT> Thank you for the clear elaboration. I see how your approach gives you a lot of leverage.  I am really enjoying your programming simplicity YouTube and Substack.  Many thanks for all the content you share.",
    "team": "T5TCAFTA9",
    "thread_ts": "1771596314.639699",
    "parent_user_id": "UGWUJUZHT",
    "blocks": [
      {
        "type": "rich_text",
        "block_id": "CfNJy",
        "elements": [
          {
            "type": "rich_text_section",
            "elements": [
              {
                "type": "user",
                "user_id": "UGWUJUZHT"
              },
              {
                "type": "text",
                "text": " Thank you for the clear elaboration. I see how your approach gives you a lot of leverage.  I am really enjoying your programming simplicity YouTube and Substack.  Many thanks for all the content you share."
              }
            ]
          }
        ]
      }
    ],
    "reactions": [
      {
        "name": "pray",
        "users": [
          "UGWUJUZHT"
        ],
        "count": 1
      }
    ],
    "channel_name": "thinking-together",
    "channel_id": "C5T9GPWFL"
  }
]
